termuxtexter/__init__.py
termuxtexter/app.py
termuxtexter/main.py
termux_texter-0.0.6.dist-info/LICENSE
termux_texter-0.0.6.dist-info/METADATA
termux_texter-0.0.6.dist-info/WHEEL
termux_texter-0.0.6.dist-info/entry_points.txt
termux_texter-0.0.6.dist-info/top_level.txt
termux_texter-0.0.6.dist-info/RECORD
