Metadata-Version: 2.1
Name: termux-texter
Version: 0.0.6
Summary: Easily send text messages using Flask and termux
Home-page: UNKNOWN
Author: Robert Wendt
Author-email: 
License: UNKNOWN
Platform: UNKNOWN
Classifier: Programming Language :: Python :: 3
Classifier: License :: OSI Approved :: MIT License
Classifier: Operating System :: OS Independent
Requires-Dist: flask
Requires-Dist: pause
